LICENSE
MANIFEST.in
README.rst
setup.py
cloudfunc/__init__.py
cloudfunc.egg-info/PKG-INFO
cloudfunc.egg-info/SOURCES.txt
cloudfunc.egg-info/dependency_links.txt
cloudfunc.egg-info/not-zip-safe
cloudfunc.egg-info/requires.txt
cloudfunc.egg-info/top_level.txt
docs/Makefile
docs/conf.py
docs/index.rst
docs/make.bat
requirements/docs.txt
requirements/test.txt
tests/__init__.py