Metadata-Version: 1.2
Name: cloudfunc
Version: 0.1.0
Summary: Cloud function development tools
Home-page: https://github.com/jadbin/cloudfunc
Author: jadbin
Author-email: jadbin.com@hotmail.com
License: MIT
Platform: UNKNOWN
Classifier: License :: OSI Approved :: MIT License
Classifier: Intended Audience :: Developers
Classifier: Programming Language :: Python
Classifier: Programming Language :: Python :: 3
Classifier: Programming Language :: Python :: 3.6
Classifier: Topic :: Software Development :: Libraries :: Python Modules
Requires-Python: >=3.6
